EDAR/__init__.py
EDAR/eda_format.py
EDAR/excel_report.py
edaexcelreport-0.2.1.dist-info/licenses/LICENSE
edaexcelreport-0.2.1.dist-info/METADATA
edaexcelreport-0.2.1.dist-info/WHEEL
edaexcelreport-0.2.1.dist-info/entry_points.txt
edaexcelreport-0.2.1.dist-info/top_level.txt
edaexcelreport-0.2.1.dist-info/RECORD
