Metadata-Version: 2.4
Name: EDAExcelReport
Version: 0.2.1
Summary: A Python package for generating detailed EDA reports in Excel format with structured insights and visualizations.
Home-page: https://github.com/rohit180497/EDAExcelReport
Author: Rohit Kosamkar, Sapna Chavan
Author-email: rohitkosamkar97@gmail.com, chavansapna12@gmail.com
Project-URL: Bug Tracker, https://github.com/rohit180497/EDAExcelReport/issues
Project-URL: Documentation, https://github.com/rohit180497/EDAExcelReport#readme
Project-URL: Source Code, https://github.com/rohit180497/EDAExcelReport
Keywords: EDA,Excel,exploratory data analysis,report,pandas,numpy,openpyxl,machine learning,data science,data analysis,EDAExcelReport,profiling,Visualization,Excel report,python EDA report
Classifier: Development Status :: 4 - Beta
Classifier: Intended Audience :: Developers
Classifier: Intended Audience :: Science/Research
Classifier: Topic :: Software Development :: Libraries :: Python Modules
Classifier: Topic :: Scientific/Engineering :: Artificial Intelligence
Classifier: Topic :: Scientific/Engineering :: Information Analysis
Classifier: Topic :: Scientific/Engineering :: Visualization
Classifier: Programming Language :: Python :: 3
Classifier: Programming Language :: Python :: 3.6
Classifier: Programming Language :: Python :: 3.7
Classifier: Programming Language :: Python :: 3.8
Classifier: Programming Language :: Python :: 3.9
Classifier: Programming Language :: Python :: 3.10
Classifier: License :: OSI Approved :: MIT License
Classifier: Operating System :: OS Independent
Requires-Python: >=3.6
License-File: LICENSE
Requires-Dist: pandas>=1.2.0
Requires-Dist: openpyxl>=3.0.0
Requires-Dist: numpy>=1.19.0
Requires-Dist: scikit-learn>=0.24.0
Requires-Dist: datetime
Dynamic: author
Dynamic: author-email
Dynamic: classifier
Dynamic: description
Dynamic: description-content-type
Dynamic: home-page
Dynamic: keywords
Dynamic: license-file
Dynamic: project-url
Dynamic: requires-dist
Dynamic: requires-python
Dynamic: summary
